theng/__init__.py
theng/args.py
theng/logging.py
theng/main.py
theng/plotting.py
theng/data/__init__.py
theng/data/a_data_object.py
theng/data/collection.py
theng/data/data_file.py
theng/data/json_file.py
theng/data/point.py
theng/data/time_series.py
theng/data/vector.py
theng/data/pathfinder/__init__.py
theng/data/pathfinder/direction.py
theng/data/pathfinder/behaviors/__init__.py
theng/data/pathfinder/behaviors/behavior.py
theng/data/pathfinder/behaviors/behavior_collection.py
theng/data/pathfinder/doors/__init__.py
theng/data/pathfinder/doors/door.py
theng/data/pathfinder/doors/door_collection.py
theng/data/pathfinder/groups/__init__.py
theng/data/pathfinder/groups/group.py
theng/data/pathfinder/groups/group_collection.py
theng/data/pathfinder/measurement_regions/__init__.py
theng/data/pathfinder/measurement_regions/measurement_region.py
theng/data/pathfinder/measurement_regions/measurement_region_collection.py
theng/data/pathfinder/occupants/__init__.py
theng/data/pathfinder/occupants/occupant.py
theng/data/pathfinder/occupants/occupant_collection.py
theng/data/pathfinder/profiles/__init__.py
theng/data/pathfinder/profiles/profile.py
theng/data/pathfinder/profiles/profile_collection.py
theng/data/pathfinder/rooms/__init__.py
theng/data/pathfinder/rooms/room.py
theng/data/pathfinder/rooms/room_collection.py
theng/data/pathfinder/summary/__init__.py
theng/data/pathfinder/summary/summary.py
theng/data/pathfinder/tags/__init__.py
theng/data/pathfinder/tags/tag.py
theng/data/pathfinder/tags/tag_collection.py
theng/data/pathfinder/targets/__init__.py
theng/data/pathfinder/targets/target.py
theng/data/pathfinder/targets/target_collection.py
theng/data/pathfinder/triggers/__init__.py
theng/data/pathfinder/triggers/trigger.py
theng/data/pathfinder/triggers/trigger_collection.py
theng/models/__init__.py
theng/models/model.py
theng/models/fds/__init__.py
theng/models/fds/fds.py
theng/models/pathfinder/__init__.py
theng/models/pathfinder/pathfinder.py
theng-0.1.8.dist-info/METADATA
theng-0.1.8.dist-info/WHEEL
theng-0.1.8.dist-info/top_level.txt
theng-0.1.8.dist-info/RECORD
